[
{"q":"\"सूर्य\" का अर्थ?","opts":["सूरज","चाँद","तारा","आकाश"],"ans":0,"hint":"दिन में चमकता है"},
{"q":"\"चाँद\" का अर्थ?","opts":["सूरज","चाँद","तारा","आकाश"],"ans":1,"hint":"रात में दिखता है"},
{"q":"\"आम\" क्या है?","opts":["फल","जानवर","रंग","स्थान"],"ans":0,"hint":"मीठा फल"},
{"q":"\"किताब\" क्या है?","opts":["पुस्तक","कलम","बैग","मेज"],"ans":0,"hint":"पढ़ने के काम आती है"},
{"q":"\"गाय\" क्या है?","opts":["जानवर","पक्षी","मछली","कीड़ा"],"ans":0,"hint":"दूध देती है"},
{"q":"\"पानी\" क्या है?","opts":["जल","दूध","रस","चाय"],"ans":0,"hint":"पीने के काम आता है"},
{"q":"\"आकाश\" क्या है?","opts":["आसमान","धरती","जल","अग्नि"],"ans":0,"hint":"ऊपर दिखता है"},
{"q":"\"पेड़\" क्या है?","opts":["पौधा","जानवर","पक्षी","वस्तु"],"ans":0,"hint":"हरा होता है"},
{"q":"\"मछली\" कहाँ रहती है?","opts":["पानी","आसमान","जमीन","पेड़"],"ans":0,"hint":"पानी में"},
{"q":"\"कुत्ता\" क्या है?","opts":["जानवर","पक्षी","मछली","कीड़ा"],"ans":0,"hint":"भौंकता है"},
{"q":"\"लाल\" क्या है?","opts":["रंग","फल","जानवर","स्थान"],"ans":0,"hint":"एक रंग"},
{"q":"\"नीला\" क्या है?","opts":["रंग","फल","जानवर","स्थान"],"ans":0,"hint":"आसमान जैसा रंग"},
{"q":"\"हरा\" क्या है?","opts":["रंग","फल","जानवर","स्थान"],"ans":0,"hint":"पेड़ का रंग"},
{"q":"\"स्कूल\" क्या है?","opts":["स्थान","जानवर","रंग","फल"],"ans":0,"hint":"जहाँ पढ़ते हैं"},
{"q":"\"शिक्षक\" कौन है?","opts":["अध्यापक","डॉक्टर","चालक","किसान"],"ans":0,"hint":"पढ़ाता है"},
{"q":"\"सेब\" क्या है?","opts":["फल","जानवर","रंग","स्थान"],"ans":0,"hint":"लाल फल"},
{"q":"\"केला\" क्या है?","opts":["फल","जानवर","रंग","स्थान"],"ans":0,"hint":"पीला फल"},
{"q":"\"कमल\" क्या है?","opts":["फूल","जानवर","फल","रंग"],"ans":0,"hint":"फूल है"},
{"q":"\"पेन\" क्या है?","opts":["कलम","किताब","बैग","मेज"],"ans":0,"hint":"लिखने के काम आता है"},
{"q":"\"कुर्सी\" क्या है?","opts":["कुर्सी","मेज","बिस्तर","दरवाज़ा"],"ans":0,"hint":"बैठने के लिए"},
{"q":"\"दरवाज़ा\" क्या है?","opts":["दरवाज़ा","खिड़की","कुर्सी","मेज"],"ans":0,"hint":"खोलते-बंद करते हैं"},
{"q":"\"खिड़की\" क्या है?","opts":["खिड़की","दरवाज़ा","कुर्सी","मेज"],"ans":0,"hint":"हवा आती है"},
{"q":"\"सूरज\" कब निकलता है?","opts":["सुबह","रात","शाम","दोपहर"],"ans":0,"hint":"सुबह"},
{"q":"\"रात\" में क्या दिखता है?","opts":["चाँद","सूरज","पेड़","गाड़ी"],"ans":0,"hint":"चाँद"},
{"q":"\"पंखा\" क्या करता है?","opts":["हवा","पानी","आग","रोशनी"],"ans":0,"hint":"हवा देता है"},
{"q":"\"बिल्ली\" क्या है?","opts":["जानवर","पक्षी","मछली","कीड़ा"],"ans":0,"hint":"म्याऊँ करती है"},
{"q":"\"हाथी\" क्या है?","opts":["जानवर","पक्षी","मछली","कीड़ा"],"ans":0,"hint":"बहुत बड़ा"},
{"q":"\"चींटी\" क्या है?","opts":["कीड़ा","जानवर","पक्षी","मछली"],"ans":0,"hint":"बहुत छोटी"},
{"q":"\"तोता\" क्या है?","opts":["पक्षी","जानवर","मछली","कीड़ा"],"ans":0,"hint":"हरा पक्षी"},
{"q":"\"कबूतर\" क्या है?","opts":["पक्षी","जानवर","मछली","कीड़ा"],"ans":0,"hint":"उड़ता है"},
{"q":"\"नदी\" क्या है?","opts":["जल","जमीन","आसमान","आग"],"ans":0,"hint":"बहती है"},
{"q":"\"समुद्र\" क्या है?","opts":["जल","जमीन","आसमान","आग"],"ans":0,"hint":"बहुत बड़ा पानी"},
{"q":"\"अग्नि\" क्या है?","opts":["आग","जल","हवा","धरती"],"ans":0,"hint":"जलती है"},
{"q":"\"धरती\" क्या है?","opts":["पृथ्वी","आसमान","जल","आग"],"ans":0,"hint":"हम रहते हैं"},
{"q":"\"हवा\" क्या है?","opts":["वायु","जल","आग","धरती"],"ans":0,"hint":"सांस लेते हैं"},
{"q":"\"जूता\" क्या है?","opts":["जूता","कमीज","पैंट","टोपी"],"ans":0,"hint":"पैर में पहनते हैं"},
{"q":"\"टोपी\" क्या है?","opts":["टोपी","जूता","कमीज","पैंट"],"ans":0,"hint":"सिर पर पहनते हैं"},
{"q":"\"कपड़ा\" क्या है?","opts":["कपड़ा","खाना","पानी","जानवर"],"ans":0,"hint":"पहनते हैं"},
{"q":"\"रोटी\" क्या है?","opts":["खाना","पेय","जानवर","स्थान"],"ans":0,"hint":"खाते हैं"},
{"q":"\"दूध\" क्या है?","opts":["पेय","खाना","जानवर","स्थान"],"ans":0,"hint":"पीते हैं"},
{"q":"\"बस\" क्या है?","opts":["वाहन","जानवर","स्थान","रंग"],"ans":0,"hint":"यातायात साधन"},
{"q":"\"कार\" क्या है?","opts":["वाहन","जानवर","स्थान","रंग"],"ans":0,"hint":"चलती है"},
{"q":"\"साइकिल\" क्या है?","opts":["वाहन","जानवर","स्थान","रंग"],"ans":0,"hint":"पैडल से चलती है"},
{"q":"\"रेल\" क्या है?","opts":["वाहन","जानवर","स्थान","रंग"],"ans":0,"hint":"पटरी पर चलती है"},
{"q":"\"हवाई जहाज\" क्या है?","opts":["वाहन","जानवर","स्थान","रंग"],"ans":0,"hint":"आसमान में उड़ता है"},
{"q":"\"घड़ी\" क्या बताती है?","opts":["समय","खाना","पानी","स्थान"],"ans":0,"hint":"समय"},
{"q":"\"दिन\" कब होता है?","opts":["सूरज","चाँद","तारा","रात"],"ans":0,"hint":"सूरज होता है"},
{"q":"\"रात\" कब होती है?","opts":["चाँद","सूरज","तारा","दिन"],"ans":0,"hint":"चाँद होता है"},
{"q":"\"काला\" क्या है?","opts":["रंग","फल","जानवर","स्थान"],"ans":0,"hint":"एक रंग"},
{"q":"\"सफेद\" क्या है?","opts":["रंग","फल","जानवर","स्थान"],"ans":0,"hint":"एक रंग"},
{"q":"\"1\" को हिंदी में क्या कहते हैं?","opts":["एक","दो","तीन","चार"],"ans":0,"hint":"पहली संख्या"},
{"q":"\"2\" को हिंदी में क्या कहते हैं?","opts":["एक","दो","तीन","चार"],"ans":1,"hint":"एक के बाद"},
{"q":"\"3\" को हिंदी में क्या कहते हैं?","opts":["एक","दो","तीन","चार"],"ans":2,"hint":"दो के बाद"},
{"q":"\"4\" को हिंदी में क्या कहते हैं?","opts":["एक","दो","तीन","चार"],"ans":3,"hint":"तीन के बाद"},
{"q":"\"5\" को हिंदी में क्या कहते हैं?","opts":["पाँच","छह","सात","आठ"],"ans":0,"hint":"चार के बाद"},
{"q":"\"माँ\" कौन है?","opts":["माता","पिता","भाई","बहन"],"ans":0,"hint":"ममता देती है"},
{"q":"\"पिता\" कौन है?","opts":["पिता","माता","भाई","बहन"],"ans":0,"hint":"पापा"},
{"q":"\"भाई\" कौन है?","opts":["भाई","पिता","माता","बहन"],"ans":0,"hint":"लड़का"},
{"q":"\"बहन\" कौन है?","opts":["बहन","पिता","माता","भाई"],"ans":0,"hint":"लड़की"},
{"q":"\"खेल\" क्या है?","opts":["खेल","खाना","जानवर","स्थान"],"ans":0,"hint":"खेलते हैं"},
{"q":"\"क्रिकेट\" क्या है?","opts":["खेल","खाना","जानवर","स्थान"],"ans":0,"hint":"खेल है"},
{"q":"\"फुटबॉल\" क्या है?","opts":["खेल","खाना","जानवर","स्थान"],"ans":0,"hint":"गेंद खेल"},
{"q":"\"गेंद\" क्या है?","opts":["गेंद","बैट","किताब","कलम"],"ans":0,"hint":"गोल होती है"},
{"q":"\"बैट\" क्या है?","opts":["बैट","गेंद","किताब","कलम"],"ans":0,"hint":"खेल में काम आता है"},
{"q":"\"बगीचा\" क्या है?","opts":["बगीचा","घर","स्कूल","सड़क"],"ans":0,"hint":"पेड़-पौधे होते हैं"},
{"q":"\"घर\" क्या है?","opts":["घर","स्कूल","बगीचा","सड़क"],"ans":0,"hint":"हम रहते हैं"},
{"q":"\"सड़क\" क्या है?","opts":["सड़क","घर","स्कूल","बगीचा"],"ans":0,"hint":"चलते हैं"},
{"q":"\"बच्चा\" कौन है?","opts":["बच्चा","बड़ा","शिक्षक","डॉक्टर"],"ans":0,"hint":"छोटा"},
{"q":"\"डॉक्टर\" क्या करता है?","opts":["इलाज","पढ़ाना","चलाना","पकाना"],"ans":0,"hint":"इलाज करता है"},
{"q":"\"रसोइया\" क्या करता है?","opts":["पकाना","चलाना","पढ़ाना","इलाज"],"ans":0,"hint":"खाना बनाता है"},
{"q":"\"किसान\" क्या करता है?","opts":["खेती","चलाना","पढ़ाना","पकाना"],"ans":0,"hint":"खेती करता है"},
{"q":"\"पुलिस\" क्या करती है?","opts":["सुरक्षा","पढ़ाना","पकाना","चलाना"],"ans":0,"hint":"सुरक्षा करती है"},
{"q":"\"खाना\" क्या है?","opts":["भोजन","पेय","जानवर","स्थान"],"ans":0,"hint":"खाते हैं"},
{"q":"\"फल\" क्या है?","opts":["फल","जानवर","स्थान","रंग"],"ans":0,"hint":"खाने की चीज"},
{"q":"\"सब्जी\" क्या है?","opts":["सब्जी","फल","जानवर","रंग"],"ans":0,"hint":"हरी होती है"}
]
